pycx2/__init__.py
pycx2/__main__.py
pycx2/cli.py
pycx2/compile.py
pycx2-1.0.3.dist-info/LICENSE
pycx2-1.0.3.dist-info/METADATA
pycx2-1.0.3.dist-info/WHEEL
pycx2-1.0.3.dist-info/entry_points.txt
pycx2-1.0.3.dist-info/top_level.txt
pycx2-1.0.3.dist-info/RECORD
